aws_utils_library/__init__.py
aws_utils_library/cognito.py
aws_utils_library/core.py
aws_utils_library/dynamodb.py
aws_utils_library/exceptions.py
aws_utils_library/s3.py
aws_utils_library/sns.py
aws_utils_library/sqs.py
aws_utils_library/stripe_helper.py
aws_utils_library-0.1.4.dist-info/licenses/LICENSE
aws_utils_library-0.1.4.dist-info/METADATA
aws_utils_library-0.1.4.dist-info/WHEEL
aws_utils_library-0.1.4.dist-info/top_level.txt
aws_utils_library-0.1.4.dist-info/RECORD
